aliyunsdkcas/__init__.py
aliyunsdkcas/endpoint.py
aliyunsdkcas/request/__init__.py
aliyunsdkcas/request/v20200407/CancelCertificateForPackageRequestRequest.py
aliyunsdkcas/request/v20200407/CancelOrderRequestRequest.py
aliyunsdkcas/request/v20200407/CreateCertificateForPackageRequestRequest.py
aliyunsdkcas/request/v20200407/CreateCertificateRequestRequest.py
aliyunsdkcas/request/v20200407/CreateCertificateWithCsrRequestRequest.py
aliyunsdkcas/request/v20200407/CreateWHClientCertificateRequest.py
aliyunsdkcas/request/v20200407/DecryptRequest.py
aliyunsdkcas/request/v20200407/DeleteCertificateRequestRequest.py
aliyunsdkcas/request/v20200407/DeletePCACertRequest.py
aliyunsdkcas/request/v20200407/DeleteUserCertificateRequest.py
aliyunsdkcas/request/v20200407/DescribeCertificateStateRequest.py
aliyunsdkcas/request/v20200407/DescribePackageStateRequest.py
aliyunsdkcas/request/v20200407/EncryptRequest.py
aliyunsdkcas/request/v20200407/GetCertWarehouseQuotaRequest.py
aliyunsdkcas/request/v20200407/GetUserCertificateDetailRequest.py
aliyunsdkcas/request/v20200407/ListCertRequest.py
aliyunsdkcas/request/v20200407/ListCertWarehouseRequest.py
aliyunsdkcas/request/v20200407/ListUserCertificateOrderRequest.py
aliyunsdkcas/request/v20200407/RenewCertificateOrderForPackageRequestRequest.py
aliyunsdkcas/request/v20200407/RevokeWHClientCertificateRequest.py
aliyunsdkcas/request/v20200407/SignRequest.py
aliyunsdkcas/request/v20200407/UploadPCACertRequest.py
aliyunsdkcas/request/v20200407/UploadUserCertificateRequest.py
aliyunsdkcas/request/v20200407/VerifyRequest.py
aliyunsdkcas/request/v20200407/__init__.py
aliyun_python_sdk_cas-1.0.18.dist-info/LICENSE
aliyun_python_sdk_cas-1.0.18.dist-info/METADATA
aliyun_python_sdk_cas-1.0.18.dist-info/WHEEL
aliyun_python_sdk_cas-1.0.18.dist-info/top_level.txt
aliyun_python_sdk_cas-1.0.18.dist-info/RECORD
